federated_learning_framework/__init__.py
federated_learning_framework/active_learning.py
federated_learning_framework/central_server.py
federated_learning_framework/client_device.py
federated_learning_framework/client_selection.py
federated_learning_framework/connection.py
federated_learning_framework/connection_manager.py
federated_learning_framework/decorators.py
federated_learning_framework/encryption.py
federated_learning_framework/error_recovery.py
federated_learning_framework/evaluation.py
federated_learning_framework/privacy.py
federated_learning_framework/progress_tracking.py
federated_learning_framework/utils.py
federated_learning_framework/models/__init__.py
federated_learning_framework/models/abstract_model.py
federated_learning_framework/models/pytorch_model.py
federated_learning_framework/models/tensorflow_model.py
federated_learning_framework-1.0.1.dist-info/licenses/LICENSE
tests/__init__.py
tests/test_active_learning.py
tests/test_central_server.py
tests/test_client_device.py
tests/test_connection.py
tests/test_connection_manager.py
tests/test_encryption.py
tests/test_utils.py
federated_learning_framework-1.0.1.dist-info/METADATA
federated_learning_framework-1.0.1.dist-info/WHEEL
federated_learning_framework-1.0.1.dist-info/top_level.txt
federated_learning_framework-1.0.1.dist-info/RECORD
