Metadata-Version: 2.4
Name: federated-learning-framework
Version: 1.0.1
Summary: A professional, modular and extensible framework for federated learning applications with privacy, security, and error recovery.
Home-page: https://github.com/mehrdaddjavadi/federated_learning_framework
Author: Mehrdad Javadi
Author-email: mehrdaddjavadi@gmail.com
Project-URL: Documentation, https://github.com/mehrdaddjavadi/federated_learning_framework
Project-URL: Source Code, https://github.com/mehrdaddjavadi/federated_learning_framework
Project-URL: Bug Tracker, https://github.com/mehrdaddjavadi/federated_learning_framework/issues
Keywords: federated learning,machine learning,deep learning,active learning,encryption,homomorphic encryption,privacy,differential privacy
Classifier: Development Status :: 4 - Beta
Classifier: Intended Audience :: Developers
Classifier: Intended Audience :: Education
Classifier: Intended Audience :: Science/Research
Classifier: Intended Audience :: Telecommunications Industry
Classifier: License :: OSI Approved :: MIT License
Classifier: Programming Language :: Python :: 3
Classifier: Programming Language :: Python :: 3.8
Classifier: Programming Language :: Python :: 3.9
Classifier: Programming Language :: Python :: 3.10
Classifier: Programming Language :: Python :: 3.11
Classifier: Topic :: Software Development :: Libraries :: Python Modules
Classifier: Topic :: Scientific/Engineering :: Artificial Intelligence
Classifier: Topic :: Security :: Cryptography
Requires-Python: >=3.8
License-File: LICENSE
Requires-Dist: numpy>=1.20.0
Requires-Dist: websockets>=10.0
Requires-Dist: cryptography>=3.4.0
Requires-Dist: scikit-learn>=0.24.0
Provides-Extra: tensorflow
Requires-Dist: tensorflow>=2.6.0; extra == "tensorflow"
Provides-Extra: pytorch
Requires-Dist: torch>=1.9.0; extra == "pytorch"
Provides-Extra: encryption
Requires-Dist: tenseal>=0.3.0; extra == "encryption"
Provides-Extra: visualization
Requires-Dist: matplotlib>=3.3.0; extra == "visualization"
Requires-Dist: pandas>=1.2.0; extra == "visualization"
Provides-Extra: dev
Requires-Dist: pytest>=6.0.0; extra == "dev"
Requires-Dist: pytest-asyncio>=0.18.0; extra == "dev"
Requires-Dist: pytest-mock>=3.6.0; extra == "dev"
Requires-Dist: black>=22.0.0; extra == "dev"
Requires-Dist: pylint>=2.0.0; extra == "dev"
Requires-Dist: mypy>=0.950; extra == "dev"
Dynamic: author
Dynamic: author-email
Dynamic: classifier
Dynamic: description
Dynamic: description-content-type
Dynamic: home-page
Dynamic: keywords
Dynamic: license-file
Dynamic: project-url
Dynamic: provides-extra
Dynamic: requires-dist
Dynamic: requires-python
Dynamic: summary
